{"textures":{"1":"modelengine:entity/dream_creature_texture"},"elements":[{"from":[5.5,6.0,6.0],"to":[9.5,11.0,10.0],"faces":{"east":{"uv":[11.25,1.875,11.75,2.375],"tintindex":0,"rotation":0,"texture":"#1"},"south":{"uv":[11.25,2.5,11.75,3.0],"tintindex":0,"rotation":0,"texture":"#1"},"north":{"uv":[11.0,6.375,11.5,6.875],"tintindex":0,"rotation":0,"texture":"#1"},"west":{"uv":[11.25,7.0,11.75,7.5],"tintindex":0,"rotation":0,"texture":"#1"},"up":{"uv":[11.75,8.125,11.25,7.625],"tintindex":0,"rotation":0,"texture":"#1"},"down":{"uv":[11.75,8.25,11.25,8.75],"tintindex":0,"rotation":0,"texture":"#1"}}}],"display":{"gui":{"rotation":[30,225,0]}}}